[
    {
        "endTime": "2020-01-24 22:19",
        "artistName": "Justin Timberlake",
        "trackName": "My Love (feat. T.I.)",
        "msPlayed": 1530
    },
    {
        "endTime": "2020-01-24 22:19",
        "artistName": "The Band",
        "trackName": "Such a Night (feat. Dr. John) - Concert Version",
        "msPlayed": 1560
    },
    {
        "endTime": "2020-01-24 22:19",
        "artistName": "The Limiñanas",
        "trackName": "Cold Was the Ground",
        "msPlayed": 2070
    },
    {
        "endTime": "2020-01-24 22:19",
        "artistName": "Sheryl Crow",
        "trackName": "A Change Would Do You Good",
        "msPlayed": 3480
    },
    {
        "endTime": "2020-01-24 22:24",
        "artistName": "Wolfmother",
        "trackName": "White Unicorn",
        "msPlayed": 304133
    },
    {
        "endTime": "2020-01-24 22:29",
        "artistName": "Warren G",
        "trackName": "Regulate",
        "msPlayed": 248866
    },
    {
        "endTime": "2020-01-24 22:33",
        "artistName": "54-40",
        "trackName": "Love You All",
        "msPlayed": 269333
    },
    {
        "endTime": "2020-01-24 22:36",
        "artistName": "Spice Girls",
        "trackName": "Spice Up Your Life",
        "msPlayed": 173666
    },
    {
        "endTime": "2020-01-24 22:40",
        "artistName": "Ozzy Osbourne",
        "trackName": "Crazy Train",
        "msPlayed": 220420
    },
    {
        "endTime": "2020-01-24 22:43",
        "artistName": "Frank Sinatra",
        "trackName": "It All Depends On You - 1998 Digital Remaster",
        "msPlayed": 2550
    },
    {
        "endTime": "2020-01-24 22:43",
        "artistName": "Manu Chao",
        "trackName": "Me Gustas Tu",
        "msPlayed": 85600
    },
    {
        "endTime": "2020-01-24 22:45",
        "artistName": "Electric Light Orchestra",
        "trackName": "Don't Bring Me Down",
        "msPlayed": 120160
    },
    {
        "endTime": "2020-01-24 22:48",
        "artistName": "Spice Girls",
        "trackName": "Wannabe",
        "msPlayed": 14072
    },
    {
        "endTime": "2020-01-24 22:48",
        "artistName": "LBL",
        "trackName": "trip on a trailer",
        "msPlayed": 2510
    },
    {
        "endTime": "2020-01-24 22:48",
        "artistName": "Spice Girls",
        "trackName": "Who Do You Think You Are",
        "msPlayed": 188577
    },
    {
        "endTime": "2020-01-24 22:51",
        "artistName": "Dusty Springfield",
        "trackName": "Spooky (Single Version)",
        "msPlayed": 164933
    },
    {
        "endTime": "2020-01-24 22:52",
        "artistName": "ABBA",
        "trackName": "SOS",
        "msPlayed": 38676
    },
    {
        "endTime": "2020-01-24 22:57",
        "artistName": "Seal",
        "trackName": "Kiss from a Rose",
        "msPlayed": 288426
    },
    {
        "endTime": "2020-01-24 23:05",
        "artistName": "Seals and Crofts",
        "trackName": "Summer Breeze",
        "msPlayed": 26045
    },
    {
        "endTime": "2020-01-24 23:07",
        "artistName": "Deerhunter",
        "trackName": "Revival",
        "msPlayed": 133666
    },
    {
        "endTime": "2020-01-24 23:22",
        "artistName": "The Vines",
        "trackName": "Ride",
        "msPlayed": 151178
    },
    {
        "endTime": "2020-01-24 23:53",
        "artistName": "The Vines",
        "trackName": "Ride",
        "msPlayed": 129832
    },
    {
        "endTime": "2020-01-24 23:57",
        "artistName": "Broken Bells",
        "trackName": "After the Disco",
        "msPlayed": 219293
    },
    {
        "endTime": "2020-01-24 23:59",
        "artistName": "Crumb",
        "trackName": "Recently Played",
        "msPlayed": 120454
    },
    {
        "endTime": "2020-01-25 00:04",
        "artistName": "Butthole Surfers",
        "trackName": "Pepper",
        "msPlayed": 297266
    },
    {
        "endTime": "2020-01-25 00:09",
        "artistName": "The Payolas",
        "trackName": "Eyes Of A Stranger",
        "msPlayed": 298040
    },
    {
        "endTime": "2020-01-25 00:14",
        "artistName": "Led Zeppelin",
        "trackName": "What Is and What Should Never Be - 1990 Remaster",
        "msPlayed": 283973
    },
    {
        "endTime": "2020-01-25 00:17",
        "artistName": "Ace of Base",
        "trackName": "All That She Wants",
        "msPlayed": 211213
    },
    {
        "endTime": "2020-01-25 00:23",
        "artistName": "The B-52's",
        "trackName": "Love Shack",
        "msPlayed": 321573
    },
    {
        "endTime": "2020-01-25 00:26",
        "artistName": "Henry Mancini",
        "trackName": "Pink Panther Theme",
        "msPlayed": 161600
    },
    {
        "endTime": "2020-01-25 00:26",
        "artistName": "Steve Miller Band",
        "trackName": "Fly Like An Eagle",
        "msPlayed": 4383
    },
    {
        "endTime": "2020-01-25 00:27",
        "artistName": "James Taylor",
        "trackName": "Fire and Rain",
        "msPlayed": 98390
    }
]